{
    "name": "cagd1-microbit-tutorials",
    "description": "",
    "dependencies": {
        "core": "*",
        "radio": "*",
        "microphone": "*"
    },
    "files": [
        "main.ts",
        "README.md",
        "l2-introduction-to-microbit.md"
    ],
    "testFiles": [
        "test.ts"
    ],
    "targetVersions": {
        "target": "7.0.61",
        "targetId": "microbit"
    },
    "supportedTargets": [
        "microbit"
    ],
    "preferredEditor": "tsprj",
    "languageRestriction": "javascript-only"
}
